liten.py
liten-0.1.6.dist-info/DESCRIPTION.rst
liten-0.1.6.dist-info/METADATA
liten-0.1.6.dist-info/RECORD
liten-0.1.6.dist-info/WHEEL
liten-0.1.6.dist-info/entry_points.txt
liten-0.1.6.dist-info/metadata.json
liten-0.1.6.dist-info/top_level.txt
