Metadata-Version: 2.0
Name: liten
Version: 0.1.6
Summary: a de-duplication command line tool
Home-page: https://github.com/nogibjj/pyli
Author: Noah Gift
Author-email: noah.gift@gmail.com
License: MIT
Download-URL: https://github.com/nogibjj/pyli
Platform: UNKNOWN
Classifier: Development Status :: 4 - Beta
Classifier: Intended Audience :: Developers
Classifier: License :: OSI Approved :: MIT License
